{
  "name": "Argentina",
  "data": [
    {
      "year": "1992",
      "bottom": 4.6,
      "middle": 44.5,
      "top": 50.9
    },
    {
      "year": "1993",
      "bottom": 4.5,
      "middle": 45.6,
      "top": 49.9
    },
    {
      "year": "1994",
      "bottom": 4.4,
      "middle": 44.6,
      "top": 51.0
    },
    {
      "year": "1995",
      "bottom": 3.8,
      "middle": 42.400000000000006,
      "top": 53.8
    },
    {
      "year": "1996",
      "bottom": 3.5,
      "middle": 42.5,
      "top": 54.0
    },
    {
      "year": "1997",
      "bottom": 3.6,
      "middle": 42.699999999999996,
      "top": 53.7
    },
    {
      "year": "1998",
      "bottom": 3.4,
      "middle": 41.5,
      "top": 55.1
    },
    {
      "year": "1999",
      "bottom": 3.5,
      "middle": 42.3,
      "top": 54.2
    },
    {
      "year": "2000",
      "bottom": 3.2,
      "middle": 41.699999999999996,
      "top": 55.1
    },
    {
      "year": "2001",
      "bottom": 2.6,
      "middle": 40.4,
      "top": 57.0
    },
    {
      "year": "2002",
      "bottom": 2.8,
      "middle": 39.400000000000006,
      "top": 57.8
    },
    {
      "year": "2003",
      "bottom": 3.2,
      "middle": 42.3,
      "top": 54.5
    },
    {
      "year": "2004",
      "bottom": 3.5,
      "middle": 44.2,
      "top": 52.3
    },
    {
      "year": "2005",
      "bottom": 3.6,
      "middle": 44.699999999999996,
      "top": 51.7
    },
    {
      "year": "2006",
      "bottom": 3.7,
      "middle": 45.599999999999994,
      "top": 50.7
    },
    {
      "year": "2007",
      "bottom": 3.9,
      "middle": 45.6,
      "top": 50.5
    },
    {
      "year": "2008",
      "bottom": 4.0,
      "middle": 47.2,
      "top": 48.8
    },
    {
      "year": "2009",
      "bottom": 4.0,
      "middle": 47.8,
      "top": 48.2
    },
    {
      "year": "2010",
      "bottom": 4.6,
      "middle": 47.4,
      "top": 48.0
    },
    {
      "year": "2011",
      "bottom": 4.8,
      "middle": 47.800000000000004,
      "top": 47.4
    },
    {
      "year": "2012",
      "bottom": 4.9,
      "middle": 48.800000000000004,
      "top": 46.3
    },
    {
      "year": "2013",
      "bottom": 5.0,
      "middle": 49.0,
      "top": 46.0
    },
    {
      "year": "2014",
      "bottom": 5.1,
      "middle": 48.3,
      "top": 46.6
    },
    {
      "year": "2015",
      "bottom": 0,
      "middle": 0,
      "top": 0
    },
    {
      "year": "2016",
      "bottom": 5.0,
      "middle": 47.4,
      "top": 47.6
    },
    {
      "year": "2017",
      "bottom": 5.2,
      "middle": 48.8,
      "top": 46.0
    }
  ]
}